.gitignore
CHANGES.txt
README.md
TODO
setup.py
djinn_auth/__init__.py
djinn_auth/__init__.pyc
djinn_auth/admin.py
djinn_auth/admin.pyc
djinn_auth/authbackend.py
djinn_auth/utils.py
djinn_auth.egg-info/PKG-INFO
djinn_auth.egg-info/SOURCES.txt
djinn_auth.egg-info/dependency_links.txt
djinn_auth.egg-info/entry_points.txt
djinn_auth.egg-info/not-zip-safe
djinn_auth.egg-info/requires.txt
djinn_auth.egg-info/top_level.txt
djinn_auth/.idea/djinn_auth.iml
djinn_auth/.idea/encodings.xml
djinn_auth/.idea/misc.xml
djinn_auth/.idea/modules.xml
djinn_auth/.idea/vcs.xml
djinn_auth/.idea/workspace.xml
djinn_auth/.idea/scopes/scope_settings.xml
djinn_auth/models/__init__.py
djinn_auth/models/__init__.pyc
djinn_auth/models/base.py
djinn_auth/models/base.pyc
djinn_auth/models/globalrole.py
djinn_auth/models/globalrole.pyc
djinn_auth/models/group.py
djinn_auth/models/group.pyc
djinn_auth/models/localpermission.py
djinn_auth/models/localpermission.pyc
djinn_auth/models/localrole.py
djinn_auth/models/localrole.pyc
djinn_auth/models/role.py
djinn_auth/models/role.pyc
djinn_auth/templatetags/__init__.py
djinn_auth/templatetags/__init__.pyc
djinn_auth/templatetags/djinn_auth_tags.py
djinn_auth/templatetags/djinn_auth_tags.pyc
djinn_auth/tests/__init__.py
djinn_auth/tests/test_authbackend.py
djinn_auth/tests/test_globalrole.py
djinn_auth/tests/test_localrole.py
djinn_auth/tests/test_permissionprotectedmixin.py
djinn_auth/views/__init__.py
djinn_auth/views/base.py