Metadata-Version: 1.1
Name: djinn-auth
Version: 1.0.6
Summary: Djinn Intranet auth module, role based
Home-page: https://github.com/PythonUnited/djinn_auth
Author: PythonUnited
Author-email: info@pythonunited.com
License: beer-ware
Keywords: Djinn role base auth
Platform: UNKNOWN
Classifier: Development Status :: 4 - Beta
Classifier: Framework :: Django
Classifier: Intended Audience :: Developers
Classifier: License :: Freely Distributable
Classifier: Programming Language :: Python
Classifier: Topic :: Internet :: WWW/HTTP :: Site Management
Classifier: Topic :: Software Development :: Libraries :: Application Frameworks
